alto/__init__.py
alto_xml-0.0.5.dist-info/LICENSE
alto_xml-0.0.5.dist-info/METADATA
alto_xml-0.0.5.dist-info/WHEEL
alto_xml-0.0.5.dist-info/top_level.txt
alto_xml-0.0.5.dist-info/RECORD
